SparkCleaner/Interface.py
SparkCleaner/__init__.py
SparkCleaner/Strategies/__init__.py
SparkCleaner/Strategies/base.py
SparkCleaner/Strategies/drop_duplicates.py
SparkCleaner/Strategies/drop_missing_values.py
SparkCleaner/Strategies/filter_negative_values.py
SparkCleaner/Strategies/filtering.py
SparkCleaner/Strategies/replace_nulls.py
SparkCleaner/Strategies/validate_columns_type.py
SparkCleaner/Strategies/validate_date.py
SparkCleaner/Strategies/validate_regex.py
SparkCleaner/logger/__init__.py
SparkCleaner/logger/logger.py
Spark_df_Cleaner-0.0.5.dist-info/METADATA
Spark_df_Cleaner-0.0.5.dist-info/WHEEL
Spark_df_Cleaner-0.0.5.dist-info/top_level.txt
Spark_df_Cleaner-0.0.5.dist-info/RECORD
